LICENSE.md
README.md
setup.py
ceotr_sensor_tracker_proxy/__init__.py
ceotr_sensor_tracker_proxy/sensor_tracker_proxy.py
ceotr_sensor_tracker_proxy.egg-info/PKG-INFO
ceotr_sensor_tracker_proxy.egg-info/SOURCES.txt
ceotr_sensor_tracker_proxy.egg-info/dependency_links.txt
ceotr_sensor_tracker_proxy.egg-info/requires.txt
ceotr_sensor_tracker_proxy.egg-info/top_level.txt
ceotr_sensor_tracker_proxy.egg-info/zip-safe